biliBV/__init__.py
biliBV-1.0.1.dist-info/LICENSE
biliBV-1.0.1.dist-info/METADATA
biliBV-1.0.1.dist-info/WHEEL
biliBV-1.0.1.dist-info/top_level.txt
biliBV-1.0.1.dist-info/RECORD
