Metadata-Version: 2.1
Name: biliBV
Version: 1.0.1
Summary: A Python Lirary that you can encode av-number to BV-string or decode BV-string.
Home-page: https://github.com/ShiSheng233/bili_BV
Author: ShiSheng
Author-email: shisheng233@dingtalk.com
License: WTFPL
Platform: UNKNOWN
Requires-Python: >=3.6
